LICENSE
MANIFEST.in
README.md
setup.py
django_twitter_feed.egg-info/PKG-INFO
django_twitter_feed.egg-info/SOURCES.txt
django_twitter_feed.egg-info/dependency_links.txt
django_twitter_feed.egg-info/not-zip-safe
django_twitter_feed.egg-info/top_level.txt
twitter_feed/__init__.py
twitter_feed/import_tweets.py
twitter_feed/models.py
twitter_feed/templates/twitter_feed/latest_tweets.html