Metadata-Version: 1.0
Name: django-twitter-feed
Version: 0.1
Summary: A simple Django app to show a Twitter feed.
Home-page: https://github.com/FrancoisConstant/django-twitter-feed
Author: Francois Constant
Author-email: francois.constant@gmail.com
License: MIT License
Platform: UNKNOWN
Classifier: Environment :: Web Environment
Classifier: Framework :: Django
Classifier: Intended Audience :: Developers
Classifier: License :: OSI Approved :: MIT License
Classifier: Operating System :: OS Independent
Classifier: Programming Language :: Python
Classifier: Topic :: Internet :: WWW/HTTP :: Dynamic Content
